{
  "projectId": "672e4a9d002a1304cba4",
  "projectName": "Cal Buddy",
  "settings": {
    "services": {
      "account": true,
      "avatars": true,
      "databases": true,
      "locale": true,
      "health": true,
      "storage": true,
      "teams": true,
      "users": true,
      "functions": true,
      "graphql": true,
      "messaging": true
    },
    "auth": {
      "methods": {
        "jwt": true,
        "phone": true,
        "invites": true,
        "anonymous": true,
        "email-otp": true,
        "magic-url": true,
        "email-password": true
      },
      "security": {
        "duration": 31536000,
        "limit": 0,
        "sessionsLimit": 10,
        "passwordHistory": 0,
        "passwordDictionary": false,
        "personalDataCheck": false,
        "sessionAlerts": false,
        "mockNumbers": []
      }
    }
  },
  "functions": [
    {
      "$id": "67471d81000c290197c6",
      "execute": ["any"],
      "name": "Send Email Function",
      "enabled": true,
      "logging": true,
      "runtime": "node-22",
      "scopes": ["users.read"],
      "events": [],
      "schedule": "",
      "timeout": 15,
      "entrypoint": "src/main.js",
      "commands": "npm install",
      "path": "functions/Send Email Function"
    }
  ]
}
